InterviewtopHulianwangMianshiBaguwenFix1/README.md
InterviewtopHulianwangMianshiBaguwenFix1/__init__.py
InterviewtopHulianwangMianshiBaguwenFix1/__main__.py
InterviewtopHulianwangMianshiBaguwenFix1/file.epub
InterviewtopHulianwangMianshiBaguwenFix1/index.html
InterviewtopHulianwangMianshiBaguwenFix1/css/__init__.py
InterviewtopHulianwangMianshiBaguwenFix1/css/annotations.css
InterviewtopHulianwangMianshiBaguwenFix1/css/main.css
InterviewtopHulianwangMianshiBaguwenFix1/css/normalize.css
InterviewtopHulianwangMianshiBaguwenFix1/css/popup.css
InterviewtopHulianwangMianshiBaguwenFix1/font/__init__.py
InterviewtopHulianwangMianshiBaguwenFix1/font/fontello.eot
InterviewtopHulianwangMianshiBaguwenFix1/font/fontello.svg
InterviewtopHulianwangMianshiBaguwenFix1/font/fontello.ttf
InterviewtopHulianwangMianshiBaguwenFix1/font/fontello.woff
InterviewtopHulianwangMianshiBaguwenFix1/img/__init__.py
InterviewtopHulianwangMianshiBaguwenFix1/img/annotator-glyph-sprite.png
InterviewtopHulianwangMianshiBaguwenFix1/img/annotator-icon-sprite.png
InterviewtopHulianwangMianshiBaguwenFix1/img/apple-touch-icon.png
InterviewtopHulianwangMianshiBaguwenFix1/img/cancelfullscreen.png
InterviewtopHulianwangMianshiBaguwenFix1/img/close.png
InterviewtopHulianwangMianshiBaguwenFix1/img/fullscreen.png
InterviewtopHulianwangMianshiBaguwenFix1/img/loader.gif
InterviewtopHulianwangMianshiBaguwenFix1/img/menu-icon.png
InterviewtopHulianwangMianshiBaguwenFix1/img/save.png
InterviewtopHulianwangMianshiBaguwenFix1/img/saved.png
InterviewtopHulianwangMianshiBaguwenFix1/img/settings-s.png
InterviewtopHulianwangMianshiBaguwenFix1/img/settings.png
InterviewtopHulianwangMianshiBaguwenFix1/img/star.png
InterviewtopHulianwangMianshiBaguwenFix1/js/__init__.py
InterviewtopHulianwangMianshiBaguwenFix1/js/epub.js
InterviewtopHulianwangMianshiBaguwenFix1/js/epub.min.js
InterviewtopHulianwangMianshiBaguwenFix1/js/epub.min.map
InterviewtopHulianwangMianshiBaguwenFix1/js/hooks.min.js
interviewtop_hulianwang_mianshi_baguwen_fix1-2025.3.25.1.dist-info/METADATA
interviewtop_hulianwang_mianshi_baguwen_fix1-2025.3.25.1.dist-info/WHEEL
interviewtop_hulianwang_mianshi_baguwen_fix1-2025.3.25.1.dist-info/entry_points.txt
interviewtop_hulianwang_mianshi_baguwen_fix1-2025.3.25.1.dist-info/top_level.txt
interviewtop_hulianwang_mianshi_baguwen_fix1-2025.3.25.1.dist-info/RECORD
